geci_cdsapi/__init__.py
geci_cdsapi/calculate_wind_speed.py
geci_cdsapi/cli.py
geci_cdsapi/init_client.py
geci_cdsapi-0.1.0.dist-info/entry_points.txt
geci_cdsapi-0.1.0.dist-info/licenses/LICENSE
geci_cdsapi-0.1.0.dist-info/WHEEL
geci_cdsapi-0.1.0.dist-info/METADATA
geci_cdsapi-0.1.0.dist-info/RECORD
